alignak_checks_snmp/__init__.py
alignak_checks_snmp-2.0.2.data/data/share/alignak/etc/arbiter/packs/resource.d/snmp.cfg
alignak_checks_snmp-2.0.2.data/data/share/alignak/etc/arbiter/packs/snmp/commands-linux.cfg
alignak_checks_snmp-2.0.2.data/data/share/alignak/etc/arbiter/packs/snmp/commands-windows.cfg
alignak_checks_snmp-2.0.2.data/data/share/alignak/etc/arbiter/packs/snmp/groups.cfg
alignak_checks_snmp-2.0.2.data/data/share/alignak/etc/arbiter/packs/snmp/services-linux.cfg
alignak_checks_snmp-2.0.2.data/data/share/alignak/etc/arbiter/packs/snmp/services-windows.cfg
alignak_checks_snmp-2.0.2.data/data/share/alignak/etc/arbiter/packs/snmp/templates.cfg
alignak_checks_snmp-2.0.2.data/data/share/alignak/etc/backend-json/snmp/commands.json
alignak_checks_snmp-2.0.2.data/data/share/alignak/etc/backend-json/snmp/hostgroups.json
alignak_checks_snmp-2.0.2.data/data/share/alignak/etc/backend-json/snmp/hosts-templates.json
alignak_checks_snmp-2.0.2.data/data/share/alignak/etc/backend-json/snmp/servicegroups.json
alignak_checks_snmp-2.0.2.data/data/share/alignak/etc/backend-json/snmp/services-templates.json
alignak_checks_snmp-2.0.2.data/data/share/alignak/etc/backend-json/snmp/setup.sh
alignak_checks_snmp-2.0.2.data/data/share/alignak/libexec/check_snmp_int.pl
alignak_checks_snmp-2.0.2.data/data/share/alignak/libexec/check_snmp_load.pl
alignak_checks_snmp-2.0.2.data/data/share/alignak/libexec/check_snmp_mem.pl
alignak_checks_snmp-2.0.2.data/data/share/alignak/libexec/check_snmp_network.pl
alignak_checks_snmp-2.0.2.data/data/share/alignak/libexec/check_snmp_process.pl
alignak_checks_snmp-2.0.2.data/data/share/alignak/libexec/check_snmp_storage.pl
alignak_checks_snmp-2.0.2.data/data/share/alignak/libexec/check_snmp_uptime.pl
alignak_checks_snmp-2.0.2.dist-info/METADATA
alignak_checks_snmp-2.0.2.dist-info/RECORD
alignak_checks_snmp-2.0.2.dist-info/WHEEL
alignak_checks_snmp-2.0.2.dist-info/top_level.txt
